boxify/__init__.py
boxify/boxify.py
boxify/understand.py
boxify-0.0.3.1.dist-info/LICENSE
boxify-0.0.3.1.dist-info/METADATA
boxify-0.0.3.1.dist-info/WHEEL
boxify-0.0.3.1.dist-info/top_level.txt
boxify-0.0.3.1.dist-info/RECORD
