Metadata-Version: 2.1
Name: boxify
Version: 0.0.3.1
Summary: Containerization for Python APIs
Home-page: https://github.com/till-io/boxify
Author: Lukas Jan Stroemsdoerfer
Author-email: ljstroemsdoerfer@gmail.com
License: MIT
Platform: UNKNOWN
